khiva/__init__.py
khiva/array.py
khiva/clustering.py
khiva/dimensionality.py
khiva/distances.py
khiva/features.py
khiva/library.py
khiva/linalg.py
khiva/matrix.py
khiva/normalization.py
khiva/polynomial.py
khiva/regression.py
khiva/regularization.py
khiva/statistics.py
tests/__init__.py
tests/unit_tests/__init__.py
tests/unit_tests/array_unit_tests.py
tests/unit_tests/clustering_unit_tests.py
tests/unit_tests/dimensionality_unit_tests.py
tests/unit_tests/distances_unit_tests.py
tests/unit_tests/features_unit_tests.py
tests/unit_tests/library_unit_tests.py
tests/unit_tests/linalg_unit_tests.py
tests/unit_tests/matrix_unit_tests.py
tests/unit_tests/normalization_unit_tests.py
tests/unit_tests/polynomial_unit_tests.py
tests/unit_tests/regression_unit_tests.py
tests/unit_tests/regularization_unit_tests.py
tests/unit_tests/statistics_unit_tests.py
khiva-0.5.0.dist-info/AUTHORS.rst
khiva-0.5.0.dist-info/LICENSE.txt
khiva-0.5.0.dist-info/METADATA
khiva-0.5.0.dist-info/WHEEL
khiva-0.5.0.dist-info/top_level.txt
khiva-0.5.0.dist-info/zip-safe
khiva-0.5.0.dist-info/RECORD
