Metadata-Version: 2.1
Name: khiva
Version: 0.5.0
Summary: Python bindings for khiva
Home-page: http://shapelets.io
Author: Shapelets.io
Author-email: dev@shapelets.io
License: MPL 2.0
Platform: UNKNOWN
Classifier: Programming Language :: Python :: 3.6
Classifier: Programming Language :: Python :: 3.5
Classifier: Operating System :: Unix
Classifier: Operating System :: Microsoft :: Windows
Classifier: Operating System :: MacOS
Classifier: Intended Audience :: Science/Research
Classifier: Topic :: Scientific/Engineering
Classifier: Topic :: Software Development
